pasban/__init__.py
pasban/core/__init__.py
pasban/core/data_types.py
pasban/core/exceptions.py
pasban/core/vars.py
pasban/db/__init__.py
pasban/db/_connector.py
pasban/db/_data_loader.py
pasban/db/word_repo.py
pasban/detector/__init__.py
pasban/detector/_base.py
pasban/detector/foreign_detector.py
pasban/detector/foreign_detector_regex.py
pasban/normalizer/__init__.py
pasban/normalizer/contextual_remover.py
pasban/normalizer/text_normalizer.py
pasban/utility/__init__.py
pasban/utility/word_claclator.py
pasban-1.0.1.dist-info/licenses/LICENSE
pasban-1.0.1.dist-info/METADATA
pasban-1.0.1.dist-info/WHEEL
pasban-1.0.1.dist-info/top_level.txt
pasban-1.0.1.dist-info/RECORD
