Metadata-Version: 2.4
Name: pasban
Version: 1.0.1
Summary: Pure Persian text processing and foreign word detection library
Author-email: Amir Hossein Abdi <you@example.com>
License: MIT
Project-URL: Homepage, https://pasbans.ir
Project-URL: Repository, https://github.com/keyaruga33/pasban-detector
Keywords: persian,text-processing,nlp,word-detector,pure-persian
Classifier: Programming Language :: Python :: 3
Classifier: License :: OSI Approved :: MIT License
Classifier: Operating System :: OS Independent
Requires-Python: >=3.9
License-File: LICENSE
Requires-Dist: requests>=2.32.5
Dynamic: license-file
